{
  "preBuild": "FCNT/M06/M06:16/V50RM44A/M06.20260312:user/release-keys",
  "postBuild": "FCNT/M06/M06:16/V51RM45A/M06.20260417:user/release-keys",
  "postTimestamp": 1776356817,
  "otaUrl": "https://android.googleapis.com/packages/ota-api/package/1c78bc2541c203108f4b775b1ec8840cb44ad558.zip",
  "sizeBytes": 47669177,
  "securityPatch": "2026-05-01",
  "sdk": "36",
  "device": "M06",
  "checkinDevice": "M06",
  "title": "システムアップデートが利用可能",
  "description": "【更新内容】（ビルド番号：V51RM45A）<br> \n・セキュリティの向上<br> \n<br>\n※インストール中は本機の電源を切らないでください。<br>\n注意事項に関する詳細は弊社ホームページをご確認ください。",
  "otaType": "incremental",
  "abType": "AB",
  "requiredCacheBytes": 0,
  "partitions": [
    "odm",
    "product",
    "system",
    "system_ext",
    "vendor",
    "vendor_dlkm"
  ],
  "hasFirmware": false,
  "hasApex": true,
  "source": "app",
  "archiveUrls": []
}