{
  "preBuild": "OnePlus/OnePlus9TMO/OnePlus9TMO:13/TP1A.220905.001/R.11ede52-254f9-1:user/release-keys",
  "postBuild": "OnePlus/OnePlus9TMO/OnePlus9TMO:13/TP1A.220905.001/R.1598164-1e317-1719a3:user/release-keys",
  "postTimestamp": 1704269709,
  "otaUrl": "https://android.googleapis.com/packages/ota-api/package/8ce118605d4b7e366a2f2b3e17c4b79b29e21afe.zip",
  "sizeBytes": 1481793161,
  "securityPatch": "2024-01-05",
  "sdk": "33",
  "device": "OnePlus9TMO",
  "checkinDevice": "OnePlus9TMO",
  "title": "LE2117_13.1.0.525(EX01) is available",
  "description": "New version: LE2117_13.1.0.525(EX01)  <p>A new software update is now available for your Android smartphone.</p> This release includes the following: <p>• Updated Android security patch to 2024-01-05.</p>   If you choose not to update now, the update will be automatically applied between 2AM and 6AM starting on January 24th, 2024.  Data rates may apply. Please refrain from turning off your device while the update is being installed. During the installation, your device will be temporarily unavailable, even for emergency calls to 9-1-1.",
  "otaType": "incremental",
  "abType": "AB",
  "requiredCacheBytes": 0,
  "partitions": [],
  "hasFirmware": false,
  "hasApex": false,
  "source": "otachecker",
  "sourceId": 664,
  "archiveUrls": []
}