{
  "preBuild": "",
  "postBuild": "TECNO/CH6i-GL/TECNO-CH6i:13/TP1A.220624.014/230629V432:user/release-keys",
  "postTimestamp": 1688053166,
  "otaUrl": "https://android.googleapis.com/packages/ota-api/package/38b8d79bb0e3be6076a8d76c1af967bf39608ba5.zip",
  "sizeBytes": 4333092485,
  "securityPatch": "2023-06-05",
  "sdk": "33",
  "device": "TECNO-CH6i",
  "checkinDevice": "TECNO-CH6i",
  "title": "Tcard_CH6i-H6921AB-T-GL-230629V432",
  "description": "Caution! This update may crash rooted devices.<br>\nPlease plug in charger to OTA upgrade when power is lower than 50%.<br>\nUpdate Version:CH6i-H6921AB-T-GL-230629V432<br>\n\nUpgrade content: <br>\n1.Upgraded the Android version from Android 12 to Android 13.<br>\n2.Upgraded the HiOS version from HiOS8.6 to HiOS13.<br>\n3.Upgraded and added some special features to improve the overall experience, including but not limited to Lightning Multi-Window, AI Gallery,Smart Network Allocation,Smart Panel、VishaPlayer、SmartScan、Screenshot、FileManager.<br>\n4.We made the OS more fluently, Discover and Have fun ：）.<br>\n\nReminding:<br>\n1.Optimized system stability and performance while fixing other issues.<br>\n2.Visit the TECNO SPOT forum (TECNO SPOT) for more information.<br>",
  "otaType": "full",
  "abType": "AB",
  "requiredCacheBytes": 0,
  "partitions": [
    "product",
    "system",
    "system_ext"
  ],
  "hasFirmware": false,
  "hasApex": true,
  "source": "otachecker",
  "sourceId": 1580,
  "archiveUrls": [
    "https://archive.org/download/ota-google-tecno-tecno-ch6i/38b8d79bb0e3be6076a8d76c1af967bf39608ba5.zip"
  ]
}