{
  "otaUrl": "https://android.googleapis.com/packages/ota-api/package/f72d1930cab5bc88b3e9dc8afc6bae03786551b5.zip",
  "fingerprint": "Fairphone/FP6/FP6:15/FP6.QREL.15.105.0/VS1C:user/release-keys",
  "manufacturer": "",
  "brand": "fairphone",
  "model": "fp6",
  "title": "The Fairphone (Gen. 6) (QREL.16.69.0) Update",
  "description": "<p>The Fairphone (Gen. 6) software <strong><u>QREL.16.69.0</u></strong> is available.<br>\nThis system update includes the following changes:\n</p>\n<h3>Resolved Issues</h3>\n<ul>\n<li>You can now successfully swap the Back and Recent buttons to match your preference</li>\n<li>Optimized background process management for smoother multitasking</li>\n<li>Fixed an issue that prevented dismissing apps from the Recents screen while the keyboard was active</li>\n<li>Fixed a delay in touch input that occasionally occurred after the device had been locked for an extended period</li>\n<li>Fixed photos occasionally not getting saved after being captured</li>\n<li>Fixed noise in video recordings captured in quiet environments</li>\n<li>Fixed an issue where audio playback on bluetooth device remained muted following the completion of a phone call</li>\n<li>General UI improvements</li>\n<br>\n<h3>Other improvements</h3>\n<ul>\n<li>Security patch level: 5th of May, 2026</li>\n<li>Simplified the bootloader unlock process</li>\n</ul>\n<br>\n<a href=\"https://support.fairphone.com/hc/en-us/articles/24463713641234-The-Fairphone-Gen-6-Release-Notes\">More information</a>\n<br><br><br>\n<hr>\n<p> Note that it may take some time for the update process to complete. It will not be possible to use your device during this time. This includes not being able to make emergency calls. <p> Please note that data charges may apply."
}
