{"firmware":[{"preBuild":"Brain/NaturalAIPhone/NaturalAIPhone:15/AQ3A.250728.001/202603010850:user/release-keys","postBuild":"Brain/NaturalAIPhone/NaturalAIPhone:15/AQ3A.250728.001/202606240112:user/release-keys","postTimestamp":1782234766,"otaUrl":"https://ota.googlezip.net/packages/ota-api/package/4b3eb07d0682e415a65e5d98e35a12f9cfe3f2e8.zip","sizeBytes":1193908918,"securityPatch":"2026-06-05","sdk":"35","title":"システムアップデート","description":"更新内容<br>\n・動作安定性の向上<br>\n・セキュリティの向上<br>\n・Natural AI機能の更新<br>\n・音声レコーダーアプリの更新","otaType":"incremental","source":"app","abType":"AB","requiredCacheBytes":0,"partitions":["odm","product","system","system_dlkm","system_ext","vendor","vendor_dlkm"],"hasFirmware":false,"hasApex":true,"archiveUrls":[]}],"builds":["Brain/NaturalAIPhone/NaturalAIPhone:15/AQ3A.250728.001/202603010850:user/release-keys"]}