{
  "preBuild": "TECNO/LE7-GL/TECNO-LE7:11/RP1A.200720.011/221114V715:user/release-keys",
  "postBuild": "TECNO/LE7-GL/TECNO-LE7:11/RP1A.200720.011/230110V728:user/release-keys",
  "postTimestamp": 1673351514,
  "otaUrl": "https://android.googleapis.com/packages/ota-api/package/08446776e12d354a61581f8bf5aaa843dbbc53a0.zip",
  "sizeBytes": 105407333,
  "securityPatch": "2023-01-05",
  "sdk": "30",
  "device": "TECNO-LE7",
  "checkinDevice": "TECNO-LE7",
  "title": "LE7-H697GHIJKL-R-GL-221114V715-230110V728_20230111162622",
  "description": "Caution! This update may crash rooted devices.<br>    \nPlease plug in charger to OTA upgrade when power is lower than 50%.<br>    \nUpdate Version:LE7-H697GHIJKL-R-GL-230110V728<br>    \n\nOptimized issues:  <br>                     \n1.Updated Google Security Patch to  January 5, 2023. <br>            \n2.Improved user experience. <br>          \n\nReminding:<br>    \n1.Optimized system stability and performance while fixing other issues.<br>     \n2.Visit the TECNO SPOT forum (TECNO SPOT) for more information.<br>",
  "otaType": "incremental",
  "abType": "AB",
  "requiredCacheBytes": 0,
  "partitions": [
    "product",
    "system",
    "system_ext",
    "vendor"
  ],
  "hasFirmware": false,
  "hasApex": false,
  "source": "otachecker",
  "sourceId": 1350,
  "archiveUrls": []
}