{
  "preBuild": "google/coral/coral:13/TP1A.221005.002/9012097:user/release-keys",
  "postBuild": "google/coral/coral:13/TP1A.221005.002.B2/9382335:user/release-keys",
  "postTimestamp": 1670460823,
  "otaUrl": "https://ota.googlezip.net/packages/ota-api/package/b4da3995abe8c07563f50111f4eaa379a6201562.zip",
  "sizeBytes": 9142396,
  "securityPatch": "2022-10-05",
  "sdk": "33",
  "device": "coral",
  "checkinDevice": "coral",
  "title": "Android 13",
  "description": "This update fixes critical bugs and improves the performance and stability of your device. Learn more at g.co/pixel/community. \n\n<p>Downloading updates over a mobile network or while roaming may cause additional charges.",
  "otaType": "incremental",
  "abType": "AB",
  "requiredCacheBytes": 0,
  "partitions": [
    "product",
    "system",
    "system_ext",
    "vendor"
  ],
  "hasFirmware": false,
  "hasApex": true,
  "source": "otachecker",
  "sourceId": 507,
  "archiveUrls": []
}