{
  "preBuild": "OnePlus/OnePlusN100METRO/OnePlusN100METRO:11/RKQ1.201217.002/2109281507:user/release-keys",
  "postBuild": "OnePlus/OnePlusN100METRO/OnePlusN100METRO:11/RKQ1.201217.002/2310091801:user/release-keys",
  "postTimestamp": 1696850028,
  "otaUrl": "https://android.googleapis.com/packages/ota-api/package/4d16838e88589a0cbfde25f8a0544e0ff0ef7708.zip",
  "sizeBytes": 162604118,
  "securityPatch": "2023-10-05",
  "sdk": "30",
  "device": "OnePlusN100METRO",
  "checkinDevice": "OnePlusN100METRO",
  "title": "11.0.14.BE82CF is available",
  "description": "New version: 11.0.14.BE82CF \n \n<p>A new software update is now available for your Android smartphone.</p> \nThis release includes the following: \n<p>• Updated Android security patch to 2023-10-05.</p> \n \nIf you choose not to update now, the update will be automatically applied between 2AM and 6AM starting on October 31st, 2023.  \nData rates may apply. \nPlease refrain from turning off your device while the update is being installed. \nDuring the installation, your device will be temporarily unavailable, even for emergency calls to 9-1-1.",
  "otaType": "incremental",
  "abType": "AB",
  "requiredCacheBytes": 0,
  "partitions": [],
  "hasFirmware": false,
  "hasApex": false,
  "source": "otachecker",
  "sourceId": 359,
  "archiveUrls": [
    "https://archive.org/download/ota-google-oneplus-oneplusn100metro/5ea0044f21812b8236c27ba6e658548f9f9e65a6.zip"
  ]
}